LICENSE.txt
MANIFEST.in
README.md
setup.cfg
setup.py
ImgQualityProcess/ImgQualityProcess.pyd
ImgQualityProcess/__init__.py
ImgQualityProcess/imQualityProcessResult.pyd
ImgQualityProcess.egg-info/PKG-INFO
ImgQualityProcess.egg-info/SOURCES.txt
ImgQualityProcess.egg-info/dependency_links.txt
ImgQualityProcess.egg-info/top_level.txt
ImgQualityProcess/Function/__init__.py
ImgQualityProcess/Function/img_quality_reduce_funtion.pyd
ImgQualityProcess/Ui/__init__.py
ImgQualityProcess/Ui/img_quality_reduce.pyd