Metadata-Version: 2.1
Name: ImgQualityProcess
Version: 0.2.1
Summary: 调整清晰度和像素减小图片内存大小
Home-page: https://alidocs.dingtalk.com/i/p/4oJRz0VRJyvmLZMydy0mV7WvjQn7MG89
Author: renlingkun
Author-email: 17891967090@163.com
Classifier: Programming Language :: Python
Requires-Python: >=3.8
License-File: LICENSE.txt
